setup2requirements/__init__.py
setup2requirements/__main__.py
setup2requirements-0.1.0.dist-info/DESCRIPTION.rst
setup2requirements-0.1.0.dist-info/METADATA
setup2requirements-0.1.0.dist-info/RECORD
setup2requirements-0.1.0.dist-info/WHEEL
setup2requirements-0.1.0.dist-info/entry_points.txt
setup2requirements-0.1.0.dist-info/metadata.json
setup2requirements-0.1.0.dist-info/top_level.txt
setup2requirements-0.1.0.dist-info/zip-safe
