Metadata-Version: 2.0
Name: setup2requirements
Version: 0.1.0
Summary: Generate requirements.txt from setup.py files.
Home-page: https://github.com/simon-engledew/setup2requirements
Author: Simon Engledew
Author-email: simon.engledew@gmail.com
License: MIT
Platform: UNKNOWN
